imds/__init__.py
imds/_dataset.py
imds/casia/__init__.py
imds/casia/casia2.py
imds/coverage/__init__.py
imds/coverage/coverage.py
imds/defacto/__init__.py
imds/defacto/copymove.py
imds/defacto/inpainting.py
imds/defacto/splicing.py
imds/imd/__init__.py
imds/imd/imd2020.py
imds/py.typed
imds/utils.py
image_manipulation_datasets-1.1.0.dist-info/LICENSE
image_manipulation_datasets-1.1.0.dist-info/METADATA
image_manipulation_datasets-1.1.0.dist-info/WHEEL
image_manipulation_datasets-1.1.0.dist-info/RECORD
