Metadata-Version: 2.3
Name: image-manipulation-datasets
Version: 1.1.0
Summary: A collection of image manipulation dataset classes implemented in PyTorch
Author: Spencer Cain
Author-email: cainspencerm@protonmail.com
Requires-Python: >=3.9
Classifier: Programming Language :: Python :: 3
Classifier: Programming Language :: Python :: 3.9
Classifier: Programming Language :: Python :: 3.10
Classifier: Programming Language :: Python :: 3.11
Classifier: Programming Language :: Python :: 3.12
Classifier: Programming Language :: Python :: 3.13
Requires-Dist: numpy (>=1.22.4,<2.0.0)
Requires-Dist: pillow (>=9.1.1,<10.0.0)
Requires-Dist: torch (>=1.11.0,<2.0.0)
